Workbook
Name \A: #REF!
Name \B: #REF!
Name \C: #REF!
Name \D: #REF!
Name \E: #REF!
Name \F: #REF!
Name \G: #REF!
Name \H: #REF!
Name \I: #REF!
Name \J: #REF!
Name \K: #REF!
Name \L: #REF!
Name \P: #REF!
Name \S: #REF!
Name __ap1: #REF!
Name __ar1: #REF!
Name __EEU2002: #REF!
Name __JV1: #REF!
Name __LA2002: #REF!
Name __m1: #REF!
Name __m10: #REF!
Name __m2: #REF!
Name __m3: #REF!
Name __m4: #REF!
Name __m5: #REF!
Name __m6: #REF!
Name __m7: #REF!
Name __m8: #REF!
Name __m9: #REF!
Name __ma2: #REF!
Name __ma3: #REF!
Name __ma4: #REF!
Name __NAT2002: #REF!
Name __pic1: OFFSET(#REF!,#REF!,0)
Name __pic10: OFFSET(#REF!,#REF!,0)
Name __pic11: OFFSET(#REF!,#REF!,0)
Name __pic2: OFFSET(#REF!,#REF!,0)
Name __pic3: OFFSET(#REF!,#REF!,0)
Name __pic4: OFFSET(#REF!,#REF!,0)
Name __pic5: OFFSET(#REF!,#REF!,0)
Name __pic6: OFFSET(#REF!,#REF!,0)
Name __pic7: OFFSET(#REF!,#REF!,0)
Name __pic8: OFFSET(#REF!,#REF!,0)
Name __pic9: OFFSET(#REF!,#REF!,0)
Name __ret1: #REF!
Name __ROA94: #REF!
Name __ROA95: #REF!
Name __ROA97: #REF!
Name __SPE1: #REF!
Name __SPE2: #REF!
Name __TYP1: #REF!
Name __TYP2: #REF!
Name _04_Amt: #REF!
Name _04_Date: #REF!
Name _04_Fee: #REF!
Name _04_Int: #REF!
Name _04_Mat: #REF!
Name _04_Pickup: #REF!
Name _04_Refi: #REF!
Name _05_Amt: #REF!

Sheet Cover
B17: =+Capital_Inputs!D7 -> Project X
B23: Debt Only Model

Sheet Debt_Model
A1: x | Y1: x
B2: =+Capital_Inputs!D7 -> Project X
B3: {=MID(CELL("filename",A1),FIND("]",CELL("filename",A1))+1,255)} -> Debt_Model
B4: £000's, unless stated otherwise
O5: =N5+1 -> 1 | P5: =O5+1 -> 2
B7: Forward Base Rate Curve
B8: Debt Model Case | E8: 0.0375 | F8: =+E8 -> 0.0375 | G8: =+F8 -> 0.0375 | H8: =+G8 -> 0.0375 | I8: =+H8 -> 0.0375 | J8: =+I8 -> 0.0375 | K8: =+J8 -> 0.0375 | L8: =+K8 -> 0.0375 | M8: =+L8 -> 0.0375 | ... X8: =+W8 -> 0.0375
B10: EBITDA Forecast | D10: =+Capital_Inputs!F28 -> 7250 | E10: =+((H10-D10)/4)+D10 -> 7467.5 | F10: =+((H10-D10)/4)+E10 -> 7685 | G10: =+((H10-D10)/4)+F10 -> 7902.5 | H10: =+D10*(1+Capital_Inputs!$F$38) -> 8120 | I10: =+((L10-H10)/4)+H10 -> 8363.6 | J10: =+((L10-H10)/4)+I10 -> 8607.2 | K10: =+((L10-H10)/4)+J10 -> 8850.8 | L10: =+H10*(1+Capital_Inputs!$F$38) -> 9094.4 | M10: =+((P10-L10)/4)+L10 -> 9367.232 | N10: =+((P10-L10)/4)+M10 -> 9640.064 | O10: =+((P10-L10)/4)+N10 -> 9912.896 | P10: =+L10*(1+Capital_Inputs!$F$38) -> 10185.728 | Q10: =+((T10-P10)/4)+P10 -> 10491.3 | R10: =+((T10-P10)/4)+Q10 -> 10796.872 | S10: =+((T10-P10)/4)+R10 -> 11102.444 | T10: =+P10*(1+Capital_Inputs!$F$38) -> 11408.015 | U10: =+((X10-T10)/4)+T10 -> 11750.256 | V10: =+((X10-T10)/4)+U10 -> 12092.496 | W10: =+((X10-T10)/4)+V10 -> 12434.737 | X10: =+T10*(1+Capital_Inputs!$F$38) -> 12776.977
B11: Month | D11: =+Capital_Inputs!F14 -> 46143 | E11: =IF(E12<=Capital_Inputs!$F$18,EOMONTH(D11,3),"") -> 46265 | F11: =IF(F12<=Capital_Inputs!$F$18,EOMONTH(E11,3),"") -> 46356 | G11: =IF(G12<=Capital_Inputs!$F$18,EOMONTH(F11,3),"") -> 46446 | H11: =IF(H12<=Capital_Inputs!$F$18,EOMONTH(G11,3),"") -> 46538 | I11: =IF(I12<=Capital_Inputs!$F$18,EOMONTH(H11,3),"") -> 46630 | J11: =IF(J12<=Capital_Inputs!$F$18,EOMONTH(I11,3),"") -> 46721 | K11: =IF(K12<=Capital_Inputs!$F$18,EOMONTH(J11,3),"") -> 46812 | L11: =IF(L12<=Capital_Inputs!$F$18,EOMONTH(K11,3),"") -> 46904 | ... X11: =IF(X12<=Capital_Inputs!$F$18,EOMONTH(W11,3),"") -> 47999
B12: Month number | D12: 0 | E12: =+D12+3 -> 3 | F12: =+E12+3 -> 6 | G12: =+F12+3 -> 9 | H12: =+G12+3 -> 12 | I12: =+H12+3 -> 15 | J12: =+I12+3 -> 18 | K12: =+J12+3 -> 21 | L12: =+K12+3 -> 24 | ... X12: =+W12+3 -> 60
B14: Returns Summary
B16: Westbrooke Net Investor IRR | C16: {=XIRR( _xlfn._xlws.FILTER(D16:X16,$D$11:$X$11<=Capital_Inputs!$F$19), _xlfn._xlws.FILTER(Debt_Model!$D$11:$X$11,Debt_Model!$D$11:$X$11<=Capital_Inputs!$F$19) )} -> 0.31972077 | D16: =+D133 -> -8540 | E16: =+E133 -> 403.125 | F16: =+F133 -> 538.125 | G16: =+G133 -> 538.125 | H16: =+H133 -> 403.125 | I16: =+I133 -> 531.04303 | J16: =+J133 -> 531.04303 | K16: =+K133 -> 531.04303 | ... X16: =+X133 -> 15074.984
B17: Westbrooke Net Investor MoM | C17: =+SUM(E17:X17)/-D17 -> 2.8535607 | D17: =+D16 -> -8540 | E17: =+E16 -> 403.125 | F17: =+F16 -> 538.125 | G17: =+G16 -> 538.125 | H17: =+H16 -> 403.125 | I17: =+I16 -> 531.04303 | J17: =+J16 -> 531.04303 | K17: =+K16 -> 531.04303 | ... X17: =+X16 -> 15074.984
B19: Debt Schedules
B21: Global Facility
B22: Opening Balance | D22: 0 | E22: =D29 -> 28000 | F22: =E29 -> 28000 | G22: =F29 -> 28000 | H22: =G29 -> 28000 | I22: =H29 -> 26583.607 | J22: =I29 -> 26583.607 | K22: =J29 -> 26583.607 | L22: =K29 -> 26583.607 | ... X22: =W29 -> 22334.426
B23: Advances | D23: =+D39+D54+D69 -> 28000 | E23: =+E39+E54+E69 -> 0 | F23: =+F39+F54+F69 -> 0 | G23: =+G39+G54+G69 -> 0 | H23: =+H39+H54+H69 -> 0 | I23: =+I39+I54+I69 -> 0 | J23: =+J39+J54+J69 -> 0 | K23: =+K39+K54+K69 -> 0 | ... X23: =+X39+X54+X69 -> 0
B24: Arranging Fee | C24: =+D24/D23 -> 0.03 | D24: =+D40+D55+D70 -> 840 | E24: =+E40+E55+E70 -> 0 | F24: =+F40+F55+F70 -> 0 | G24: =+G40+G55+G70 -> 0 | H24: =+H40+H55+H70 -> 0 | I24: =+I40+I55+I70 -> 0 | J24: =+J40+J55+J70 -> 0 | K24: =+K40+K55+K70 -> 0 | ... X24: =+X40+X55+X70 -> 0
B25: Interest Cash Paid | C25: =(AVERAGE(E25:X25)/AVERAGE(E22:X22)*4) -> 0.1362741 | E25: =+E41+E56+E71 -> 930 | F25: =+F41+F56+F71 -> 930 | G25: =+G41+G56+G71 -> 930 | H25: =+H41+H56+H71 -> 930 | I25: =+I41+I56+I71 -> 893.70492 | J25: =+J41+J56+J71 -> 893.70492 | K25: =+K41+K56+K71 -> 893.70492 | L25: =+L41+L56+L71 -> 893.70492 | ... X25: =+X41+X56+X71 -> 784.81967
B26: Interest PIK | C26: =AVERAGE(E26:X26)/AVERAGE(E22:X22)*4 -> 0 | E26: =+E57+E72+E42 -> 0 | F26: =+F57+F72+F42 -> 0 | G26: =+G57+G72+G42 -> 0 | H26: =+H57+H72+H42 -> 0 | I26: =+I57+I72+I42 -> 0 | J26: =+J57+J72+J42 -> 0 | K26: =+K57+K72+K42 -> 0 | L26: =+L57+L72+L42 -> 0 | ... X26: =+X57+X72+X42 -> 0
B27: Amortisation | C27: =-AVERAGE(E27:X27)/AVERAGE(E22:X22)*4 -> 0.22511725 | H27: =+SUM(H43:H44,H58:H59,H73:H74) -> -1416.3934 | L27: =+SUM(L43:L44,L58:L59,L73:L74) -> -1416.3934 | P27: =+SUM(P43:P44,P58:P59,P73:P74) -> -1416.3934 | T27: =+SUM(T43:T44,T58:T59,T73:T74) -> -1416.3934 | X27: =+SUM(X43:X44,X58:X59,X73:X74) -> -1416.3934
B28: Repayments | E28: =IF(OR(E$12=Capital_Inputs!$F$18,E27<0),+E46+E61+E76,0) -> 0 | F28: =IF(OR(F$12=Capital_Inputs!$F$18,F27<0),+F46+F61+F76,0) -> 0 | G28: =IF(OR(G$12=Capital_Inputs!$F$18,G27<0),+G46+G61+G76,0) -> 0 | H28: =IF(OR(H$12=Capital_Inputs!$F$18,H27<0),+H46+H61+H76,0) -> -1416.3934 | I28: =IF(OR(I$12=Capital_Inputs!$F$18,I27<0),+I46+I61+I76,0) -> 0 | J28: =IF(OR(J$12=Capital_Inputs!$F$18,J27<0),+J46+J61+J76,0) -> 0 | K28: =IF(OR(K$12=Capital_Inputs!$F$18,K27<0),+K46+K61+K76,0) -> 0 | L28: =IF(OR(L$12=Capital_Inputs!$F$18,L27<0),+L46+L61+L76,0) -> -1416.3934 | ... X28: =IF(OR(X$12=Capital_Inputs!$F$18,X27<0),+X46+X61+X76,0) -> -22334.426
B29: Closing Balance | D29: =D22+D23+D28+D26 -> 28000 | E29: =E22+E23+E28+E26 -> 28000 | F29: =F22+F23+F28+F26 -> 28000 | G29: =G22+G23+G28+G26 -> 28000 | H29: =H22+H23+H28+H26 -> 26583.607 | I29: =I22+I23+I28+I26 -> 26583.607 | J29: =J22+J23+J28+J26 -> 26583.607 | K29: =K22+K23+K28+K26 -> 26583.607 | ... X29: =X22+X23+X28+X26 -> 7.2759576e-12
B31: Global Contractual IRR | C31: {=XIRR( _xlfn._xlws.FILTER(D31:X31,$D$11:$X$11<=Capital_Inputs!$F$19), _xlfn._xlws.FILTER(Debt_Model!$D$11:$X$11,Debt_Model!$D$11:$X$11<=Capital_Inputs!$F$19) )} -> 0.14917895 | D31: =-D23+D24 -> -27160 | E31: =+E25-E28-E23+E24 -> 930 | F31: =+F25-F28-F23+F24 -> 930 | G31: =+G25-G28-G23+G24 -> 930 | H31: =+H25-H28-H23+H24 -> 2346.3934 | I31: =+I25-I28-I23+I24 -> 893.70492 | J31: =+J25-J28-J23+J24 -> 893.70492 | K31: =+K25-K28-K23+K24 -> 893.70492 | L31: =+L25-L28-L23+L24 -> 2310.0984 | ... X31: =+X25-X28-X23+X24 -> 23119.246
B32: Global Contractual MoM | C32: =+SUM(E32:X32)/-D32 -> 1.6623047 | D32: =+D31 -> -27160 | E32: =+E31 -> 930 | F32: =+F31 -> 930 | G32: =+G31 -> 930 | H32: =+H31 -> 2346.3934 | I32: =+I31 -> 893.70492 | J32: =+J31 -> 893.70492 | K32: =+K31 -> 893.70492 | ... X32: =+X31 -> 23119.246
B34: Global Total IRR | C34: {=XIRR( _xlfn._xlws.FILTER(D34:X34,$D$11:$X$11<=Capital_Inputs!$F$19), _xlfn._xlws.FILTER(Debt_Model!$D$11:$X$11,Debt_Model!$D$11:$X$11<=Capital_Inputs!$F$19) )} -> 0.17984616 | D34: =D31+B89 -> -27159.9 | E34: =+E31+IF(E12=Capital_Inputs!$F$18,E92,0) -> 930 | F34: =+F31+IF(F12=Capital_Inputs!$F$18,F92,0) -> 930 | G34: =+G31+IF(G12=Capital_Inputs!$F$18,G92,0) -> 930 | H34: =+H31+IF(H12=Capital_Inputs!$F$18,H92,0) -> 2346.3934 | I34: =+I31+IF(I12=Capital_Inputs!$F$18,I92,0) -> 893.70492 | J34: =+J31+IF(J12=Capital_Inputs!$F$18,J92,0) -> 893.70492 | K34: =+K31+IF(K12=Capital_Inputs!$F$18,K92,0) -> 893.70492 | L34: =+L31+IF(L12=Capital_Inputs!$F$18,L92,0) -> 2310.0984 | ... X34: =+X31+IF(X12=Capital_Inputs!$F$18,X92,0) -> 28551.99
B35: Global Total MoM | C35: =+SUM(E35:X35)/-D35 -> 1.862339 | D35: =+D34 -> -27159.9 | E35: =+E34 -> 930 | F35: =+F34 -> 930 | G35: =+G34 -> 930 | H35: =+H34 -> 2346.3934 | I35: =+I34 -> 893.70492 | J35: =+J34 -> 893.70492 | K35: =+K34 -> 893.70492 | ... X35: =+X34 -> 28551.99
B37: =+Capital_Inputs!F23 -> Unitranche
B38: Opening Balance | D38: 0 | E38: =D47 -> 18000 | F38: =E47 -> 18000 | G38: =F47 -> 18000 | H38: =G47 -> 18000 | I38: =H47 -> 16583.607 | J38: =I47 -> 16583.607 | K38: =J47 -> 16583.607 | L38: =K47 -> 16583.607 | ... X38: =W47 -> 12334.426
B39: Advances | D39: =+Capital_Inputs!F44*1000 -> 18000
B40: Arranging Fee | C40: =+Capital_Inputs!F46 -> 0.03 | D40: =D39*C40 -> 540
B41: Interest Cash Paid | C41: =+Capital_Inputs!F47 -> 0.065 | E41: =IF($C41=0,0,E38*(0.25*($C41+E$8))) -> 461.25 | F41: =IF($C41=0,0,F38*(0.25*($C41+F$8))) -> 461.25 | G41: =IF($C41=0,0,G38*(0.25*($C41+G$8))) -> 461.25 | H41: =IF($C41=0,0,H38*(0.25*($C41+H$8))) -> 461.25 | I41: =IF($C41=0,0,I38*(0.25*($C41+I$8))) -> 424.95492 | J41: =IF($C41=0,0,J38*(0.25*($C41+J$8))) -> 424.95492 | K41: =IF($C41=0,0,K38*(0.25*($C41+K$8))) -> 424.95492 | L41: =IF($C41=0,0,L38*(0.25*($C41+L$8))) -> 424.95492 | ... X41: =IF($C41=0,0,X38*(0.25*($C41+X$8))) -> 316.06967
B42: Interest PIK | C42: =+Capital_Inputs!F48 -> 0 | E42: =E$38*($C42*0.25) -> 0 | F42: =F$38*($C42*0.25) -> 0 | G42: =G$38*($C42*0.25) -> 0 | H42: =H$38*($C42*0.25) -> 0 | I42: =I$38*($C42*0.25) -> 0 | J42: =J$38*($C42*0.25) -> 0 | K42: =K$38*($C42*0.25) -> 0 | L42: =L$38*($C42*0.25) -> 0 | ... X42: =X$38*($C42*0.25) -> 0
B43: Amortisation | C43: =+Capital_Inputs!F49 -> 0.4 | H43: =IF(AND(H38>0,$C44=FALSE),-($C43*$D39)/Capital_Inputs!$F$20,0) -> -1416.3934 | L43: =IF(AND(L38>0,$C44=FALSE),-($C43*$D39)/Capital_Inputs!$F$20,0) -> -1416.3934 | P43: =IF(AND(P38>0,$C44=FALSE),-($C43*$D39)/Capital_Inputs!$F$20,0) -> -1416.3934 | T43: =IF(AND(T38>0,$C44=FALSE),-($C43*$D39)/Capital_Inputs!$F$20,0) -> -1416.3934 | X43: =IF(AND(X38>0,$C44=FALSE),-($C43*$D39)/Capital_Inputs!$F$20,0) -> -1416.3934
B44: Sculpted | C44: FALSE
B45: Other mechanism
B46: Repayments | E46: =IF(Debt_Model!E$12=Capital_Inputs!$F$18,-E38-E42,IF(SUM(E43:E45)<0,SUM(E43:E45),0)) -> 0 | F46: =IF(Debt_Model!F$12=Capital_Inputs!$F$18,-F38-F42,IF(SUM(F43:F45)<0,SUM(F43:F45),0)) -> 0 | G46: =IF(Debt_Model!G$12=Capital_Inputs!$F$18,-G38-G42,IF(SUM(G43:G45)<0,SUM(G43:G45),0)) -> 0 | H46: =IF(Debt_Model!H$12=Capital_Inputs!$F$18,-H38-H42,IF(SUM(H43:H45)<0,SUM(H43:H45),0)) -> -1416.3934 | I46: =IF(Debt_Model!I$12=Capital_Inputs!$F$18,-I38-I42,IF(SUM(I43:I45)<0,SUM(I43:I45),0)) -> 0 | J46: =IF(Debt_Model!J$12=Capital_Inputs!$F$18,-J38-J42,IF(SUM(J43:J45)<0,SUM(J43:J45),0)) -> 0 | K46: =IF(Debt_Model!K$12=Capital_Inputs!$F$18,-K38-K42,IF(SUM(K43:K45)<0,SUM(K43:K45),0)) -> 0 | L46: =IF(Debt_Model!L$12=Capital_Inputs!$F$18,-L38-L42,IF(SUM(L43:L45)<0,SUM(L43:L45),0)) -> -1416.3934 | ... X46: =IF(Debt_Model!X$12=Capital_Inputs!$F$18,-X38-X42,IF(SUM(X43:X45)<0,SUM(X43:X45),0)) -> -12334.426
B47: Closing Balance | D47: =D38+D39-D46 -> 18000 | E47: =E38+E39+E46+E42 -> 18000 | F47: =F38+F39+F46+F42 -> 18000 | G47: =G38+G39+G46+G42 -> 18000 | H47: =H38+H39+H46+H42 -> 16583.607 | I47: =I38+I39+I46+I42 -> 16583.607 | J47: =J38+J39+J46+J42 -> 16583.607 | K47: =K38+K39+K46+K42 -> 16583.607 | L47: =L38+L39+L46+L42 -> 15167.213 | ... X47: =X38+X39+X46+X42 -> 0
B49: =B37& " Gross IRR" -> Unitranche Gross IRR | C49: {=XIRR( _xlfn._xlws.FILTER(D49:X49,$D$11:$X$11<=Capital_Inputs!$F$19), _xlfn._xlws.FILTER(Debt_Model!$D$11:$X$11,Debt_Model!$D$11:$X$11<=Capital_Inputs!$F$19) )} -> 0.12804263 | D49: =-D39+D40 -> -17460 | E49: =E41-E46 -> 461.25 | F49: =F41-F46 -> 461.25 | G49: =G41-G46 -> 461.25 | H49: =H41-H46 -> 1877.6434 | I49: =I41-I46 -> 424.95492 | J49: =J41-J46 -> 424.95492 | K49: =K41-K46 -> 424.95492 | L49: =L41-L46 -> 1841.3484 | ... W49: =W41-W46 -> 316.06967 | X49: =X41-X46-SUM(X43:X44) -> 14066.889
B50: =$B$37& " Gross MoM" -> Unitranche Gross MoM | C50: =+SUM(E50:X50)/-D50 -> 1.5572503 | D50: =+D49 -> -17460 | E50: =+E49 -> 461.25 | F50: =+F49 -> 461.25 | G50: =+G49 -> 461.25 | H50: =+H49 -> 1877.6434 | I50: =+I49 -> 424.95492 | J50: =+J49 -> 424.95492 | K50: =+K49 -> 424.95492 | ... X50: =+X49 -> 14066.889
B52: =+Capital_Inputs!F24 -> Preferred Equity
B53: Opening Balance | D53: 0 | E53: =D62 -> 10000 | F53: =E62 -> 10000 | G53: =F62 -> 10000 | H53: =G62 -> 10000 | I53: =H62 -> 10000 | J53: =I62 -> 10000 | K53: =J62 -> 10000 | L53: =K62 -> 10000 | ... X53: =W62 -> 10000
B54: Advances | D54: =+Capital_Inputs!F55*1000 -> 10000
B55: Arranging Fee | C55: =+Capital_Inputs!F57 -> 0.03 | D55: =IF(D11=Capital_Inputs!$F$58,Capital_Inputs!$F$57*Capital_Inputs!$F$59*Capital_Inputs!$F$54*1000,0)+IF(AND(Debt_Model!D11>=Capital_Inputs!$F$60,D54>0,D53=0),Capital_Inputs!$F$61*Capital_Inputs!$F$57*Capital_Inputs!$F$55*1000,0) -> 300 | E55: =IF(E11=Capital_Inputs!$F$58,Capital_Inputs!$F$57*Capital_Inputs!$F$59*Capital_Inputs!$F$54*1000,0)+IF(AND(Debt_Model!E11>=Capital_Inputs!$F$60,E54>0,E53=0),Capital_Inputs!$F$61*Capital_Inputs!$F$57*Capital_Inputs!$F$55*1000,0) -> 0 | F55: =IF(F11=Capital_Inputs!$F$58,Capital_Inputs!$F$57*Capital_Inputs!$F$59*Capital_Inputs!$F$54*1000,0)+IF(AND(Debt_Model!F11>=Capital_Inputs!$F$60,F54>0,F53=0),Capital_Inputs!$F$61*Capital_Inputs!$F$57*Capital_Inputs!$F$55*1000,0) -> 0 | G55: =IF(G11=Capital_Inputs!$F$58,Capital_Inputs!$F$57*Capital_Inputs!$F$59*Capital_Inputs!$F$54*1000,0)+IF(AND(Debt_Model!G11>=Capital_Inputs!$F$60,G54>0,G53=0),Capital_Inputs!$F$61*Capital_Inputs!$F$57*Capital_Inputs!$F$55*1000,0) -> 0 | H55: =IF(H11=Capital_Inputs!$F$58,Capital_Inputs!$F$57*Capital_Inputs!$F$59*Capital_Inputs!$F$54*1000,0)+IF(AND(Debt_Model!H11>=Capital_Inputs!$F$60,H54>0,H53=0),Capital_Inputs!$F$61*Capital_Inputs!$F$57*Capital_Inputs!$F$55*1000,0) -> 0 | I55: =IF(I11=Capital_Inputs!$F$58,Capital_Inputs!$F$57*Capital_Inputs!$F$59*Capital_Inputs!$F$54*1000,0)+IF(AND(Debt_Model!I11>=Capital_Inputs!$F$60,I54>0,I53=0),Capital_Inputs!$F$61*Capital_Inputs!$F$57*Capital_Inputs!$F$55*1000,0) -> 0 | J55: =IF(J11=Capital_Inputs!$F$58,Capital_Inputs!$F$57*Capital_Inputs!$F$59*Capital_Inputs!$F$54*1000,0)+IF(AND(Debt_Model!J11>=Capital_Inputs!$F$60,J54>0,J53=0),Capital_Inputs!$F$61*Capital_Inputs!$F$57*Capital_Inputs!$F$55*1000,0) -> 0 | K55: =IF(K11=Capital_Inputs!$F$58,Capital_Inputs!$F$57*Capital_Inputs!$F$59*Capital_Inputs!$F$54*1000,0)+IF(AND(Debt_Model!K11>=Capital_Inputs!$F$60,K54>0,K53=0),Capital_Inputs!$F$61*Capital_Inputs!$F$57*Capital_Inputs!$F$55*1000,0) -> 0 | ... X55: =IF(X11=Capital_Inputs!$F$58,Capital_Inputs!$F$57*Capital_Inputs!$F$59*Capital_Inputs!$F$54*1000,0)+IF(AND(Debt_Model!X11>=Capital_Inputs!$F$60,X54>0,X53=0),Capital_Inputs!$F$61*Capital_Inputs!$F$57*Capital_Inputs!$F$55*1000,0) -> 0
B56: Interest Cash Paid | C56: =+Capital_Inputs!F62 -> 0.15 | E56: =IF($C56=0,0,E53*(0.25*($C56+E$8))) -> 468.75 | F56: =IF($C56=0,0,F53*(0.25*($C56+F$8))) -> 468.75 | G56: =IF($C56=0,0,G53*(0.25*($C56+G$8))) -> 468.75 | H56: =IF($C56=0,0,H53*(0.25*($C56+H$8))) -> 468.75 | I56: =IF($C56=0,0,I53*(0.25*($C56+I$8))) -> 468.75 | J56: =IF($C56=0,0,J53*(0.25*($C56+J$8))) -> 468.75 | K56: =IF($C56=0,0,K53*(0.25*($C56+K$8))) -> 468.75 | L56: =IF($C56=0,0,L53*(0.25*($C56+L$8))) -> 468.75 | ... X56: =IF($C56=0,0,X53*(0.25*($C56+X$8))) -> 468.75
B57: Interest PIK | C57: =+Capital_Inputs!F63 -> 0 | E57: =E$53*($C57/4) -> 0 | F57: =F$53*($C57/4) -> 0 | G57: =G$53*($C57/4) -> 0 | H57: =H$53*($C57/4) -> 0 | I57: =I$53*($C57/4) -> 0 | J57: =J$53*($C57/4) -> 0 | K57: =K$53*($C57/4) -> 0 | L57: =L$53*($C57/4) -> 0 | ... X57: =X$53*($C57/4) -> 0
B58: Amortisation | C58: =+Capital_Inputs!F64 -> 0 | H58: =IF(AND(H53>0,$C59=FALSE),-($C58*$D54)/Capital_Inputs!$F$20,0) -> 0 | L58: =IF(AND(L53>0,$C59=FALSE),-($C58*$D54)/Capital_Inputs!$F$20,0) -> 0 | P58: =IF(AND(P53>0,$C59=FALSE),-($C58*$D54)/Capital_Inputs!$F$20,0) -> 0 | T58: =IF(AND(T53>0,$C59=FALSE),-($C58*$D54)/Capital_Inputs!$F$20,0) -> 0 | X58: =IF(AND(X53>0,$C59=FALSE),-($C58*$D54)/Capital_Inputs!$F$20,0) -> 0
B59: Sculpted | C59: FALSE
B60: Other mechanism
B61: Repayments | E61: =IF(Debt_Model!E$12=Capital_Inputs!$F$18,-E53-E57,IF(SUM(E58:E60)<0,SUM(E58:E60),0)) -> 0 | F61: =IF(Debt_Model!F$12=Capital_Inputs!$F$18,-F53-F57,IF(SUM(F58:F60)<0,SUM(F58:F60),0)) -> 0 | G61: =IF(Debt_Model!G$12=Capital_Inputs!$F$18,-G53-G57,IF(SUM(G58:G60)<0,SUM(G58:G60),0)) -> 0 | H61: =IF(Debt_Model!H$12=Capital_Inputs!$F$18,-H53-H57,IF(SUM(H58:H60)<0,SUM(H58:H60),0)) -> 0 | I61: =IF(Debt_Model!I$12=Capital_Inputs!$F$18,-I53-I57,IF(SUM(I58:I60)<0,SUM(I58:I60),0)) -> 0 | J61: =IF(Debt_Model!J$12=Capital_Inputs!$F$18,-J53-J57,IF(SUM(J58:J60)<0,SUM(J58:J60),0)) -> 0 | K61: =IF(Debt_Model!K$12=Capital_Inputs!$F$18,-K53-K57,IF(SUM(K58:K60)<0,SUM(K58:K60),0)) -> 0 | L61: =IF(Debt_Model!L$12=Capital_Inputs!$F$18,-L53-L57,IF(SUM(L58:L60)<0,SUM(L58:L60),0)) -> 0 | ... X61: =IF(Debt_Model!X$12=Capital_Inputs!$F$18,-X53-X57,IF(SUM(X58:X60)<0,SUM(X58:X60),0)) -> -10000
B62: Closing Balance | D62: =D53+D54+D61 -> 10000 | E62: =E53+E54+E61+E57 -> 10000 | F62: =F53+F54+F61+F57 -> 10000 | G62: =G53+G54+G61+G57 -> 10000 | H62: =H53+H54+H61+H57 -> 10000 | I62: =I53+I54+I61+I57 -> 10000 | J62: =J53+J54+J61+J57 -> 10000 | K62: =K53+K54+K61+K57 -> 10000 | L62: =L53+L54+L61+L57 -> 10000 | ... X62: =X53+X54+X61+X57 -> 0
B64: =$B$52& " Gross IRR" -> Preferred Equity Gross IRR | C64: {=XIRR( _xlfn._xlws.FILTER(D64:X64,$D$11:$X$11<=Capital_Inputs!$F$19), _xlfn._xlws.FILTER(Debt_Model!$D$11:$X$11,Debt_Model!$D$11:$X$11<=Capital_Inputs!$F$19) )} -> 0.20635907 | D64: =-D54+D56+D55-D61 -> -9700 | E64: =-E54+E56+E55-E61 -> 468.75 | F64: =-F54+F56+F55-F61 -> 468.75 | G64: =-G54+G56+G55-G61 -> 468.75 | H64: =-H54+H56+H55-H61 -> 468.75 | I64: =-I54+I56+I55-I61 -> 468.75 | J64: =-J54+J56+J55-J61 -> 468.75 | K64: =-K54+K56+K55-K61 -> 468.75 | ... X64: =-X54+X56+X55-X61 -> 10468.75
B65: =$B$52& " Gross MoM" -> Preferred Equity Gross MoM | C65: =+SUM(E65:X65)/-D65 -> 1.9974227 | D65: =+D64 -> -9700 | E65: =+E64 -> 468.75 | F65: =+F64 -> 468.75 | G65: =+G64 -> 468.75 | H65: =+H64 -> 468.75 | I65: =+I64 -> 468.75 | J65: =+J64 -> 468.75 | K65: =+K64 -> 468.75 | ... X65: =+X64 -> 10468.75
B67: =+Capital_Inputs!F25 -> 0
B68: Opening Balance | D68: 0 | E68: =D77 -> 0 | F68: =E77 -> 0 | G68: =F77 -> 0 | H68: =G77 -> 0 | I68: =H77 -> 0 | J68: =I77 -> 0 | K68: =J77 -> 0 | L68: =K77 -> 0 | ... X68: =W77 -> 0
B69: Advances | D69: =+Capital_Inputs!F69*1000 -> 0
B70: Arranging Fee | C70: =+Capital_Inputs!F71 -> 0 | D70: =D69*C70 -> 0
B71: Interest Cash Paid | C71: =+Capital_Inputs!F72 -> 0 | E71: =IF($C71=0,0,E68*(0.25*($C71+E$8))) -> 0 | F71: =IF($C71=0,0,F68*(0.25*($C71+F$8))) -> 0 | G71: =IF($C71=0,0,G68*(0.25*($C71+G$8))) -> 0 | H71: =IF($C71=0,0,H68*(0.25*($C71+H$8))) -> 0 | I71: =IF($C71=0,0,I68*(0.25*($C71+I$8))) -> 0 | J71: =IF($C71=0,0,J68*(0.25*($C71+J$8))) -> 0 | K71: =IF($C71=0,0,K68*(0.25*($C71+K$8))) -> 0 | L71: =IF($C71=0,0,L68*(0.25*($C71+L$8))) -> 0 | ... X71: =IF($C71=0,0,X68*(0.25*($C71+X$8))) -> 0
B72: Interest PIK | C72: =+Capital_Inputs!F73 -> 0 | E72: =E$68*($C72*0.25) -> 0 | F72: =F$68*($C72*0.25) -> 0 | G72: =G$68*($C72*0.25) -> 0 | H72: =H$68*($C72*0.25) -> 0 | I72: =I$68*($C72*0.25) -> 0 | J72: =J$68*($C72*0.25) -> 0 | K72: =K$68*($C72*0.25) -> 0 | L72: =L$68*($C72*0.25) -> 0 | ... X72: =X$68*($C72*0.25) -> 0
B73: Amortisation | C73: =+Capital_Inputs!F74 -> 0 | H73: =IF(AND(H68>0,$C74=FALSE),-($C73*$D69)/Capital_Inputs!$F$20,0) -> 0 | L73: =IF(AND(L68>0,$C74=FALSE),-($C73*$D69)/Capital_Inputs!$F$20,0) -> 0 | P73: =IF(AND(P68>0,$C74=FALSE),-($C73*$D69)/Capital_Inputs!$F$20,0) -> 0 | T73: =IF(AND(T68>0,$C74=FALSE),-($C73*$D69)/Capital_Inputs!$F$20,0) -> 0 | X73: =IF(AND(X68>0,$C74=FALSE),-($C73*$D69)/Capital_Inputs!$F$20,0) -> 0
B74: Sculpted | C74: FALSE
B75: Other mechanism
B76: Repayments | E76: =IF(Debt_Model!E$12=Capital_Inputs!$F$18,-E68-E72,IF(SUM(Debt_Model!E73:E75)<0,SUM(E73:E75),0)) -> 0 | F76: =IF(Debt_Model!F$12=Capital_Inputs!$F$18,-F68-F72,IF(SUM(Debt_Model!F73:F75)<0,SUM(F73:F75),0)) -> 0 | G76: =IF(Debt_Model!G$12=Capital_Inputs!$F$18,-G68-G72,IF(SUM(Debt_Model!G73:G75)<0,SUM(G73:G75),0)) -> 0 | H76: =IF(Debt_Model!H$12=Capital_Inputs!$F$18,-H68-H72,IF(SUM(Debt_Model!H73:H75)<0,SUM(H73:H75),0)) -> 0 | I76: =IF(Debt_Model!I$12=Capital_Inputs!$F$18,-I68-I72,IF(SUM(Debt_Model!I73:I75)<0,SUM(I73:I75),0)) -> 0 | J76: =IF(Debt_Model!J$12=Capital_Inputs!$F$18,-J68-J72,IF(SUM(Debt_Model!J73:J75)<0,SUM(J73:J75),0)) -> 0 | K76: =IF(Debt_Model!K$12=Capital_Inputs!$F$18,-K68-K72,IF(SUM(Debt_Model!K73:K75)<0,SUM(K73:K75),0)) -> 0 | L76: =IF(Debt_Model!L$12=Capital_Inputs!$F$18,-L68-L72,IF(SUM(Debt_Model!L73:L75)<0,SUM(L73:L75),0)) -> 0 | ... X76: =IF(Debt_Model!X$12=Capital_Inputs!$F$18,-X68-X72,IF(SUM(Debt_Model!X73:X75)<0,SUM(X73:X75),0)) -> 0
B77: Closing Balance | D77: =D68+D69+D76 -> 0 | E77: =E68+E69+E76+E72 -> 0 | F77: =F68+F69+F76+F72 -> 0 | G77: =G68+G69+G76+G72 -> 0 | H77: =H68+H69+H76+H72 -> 0 | I77: =I68+I69+I76+I72 -> 0 | J77: =J68+J69+J76+J72 -> 0 | K77: =K68+K69+K76+K72 -> 0 | L77: =L68+L69+L76+L72 -> 0 | ... X77: =X68+X69+X76+X72 -> 0
B79: =B67& " Gross IRR" -> 0 Gross IRR | C79: {=XIRR( _xlfn._xlws.FILTER(D79:X79,$D$11:$X$11<=Capital_Inputs!$F$19), _xlfn._xlws.FILTER(Debt_Model!$D$11:$X$11,Debt_Model!$D$11:$X$11<=Capital_Inputs!$F$19) )} -> #NUM! | D79: =-D69+D70 -> 0 | E79: =E71-E76 -> 0 | F79: =F71-F76 -> 0 | G79: =G71-G76 -> 0 | H79: =H71-H76 -> 0 | I79: =I71-I76 -> 0 | J79: =J71-J76 -> 0 | K79: =K71-K76 -> 0 | L79: =L71-L76 -> 0 | ... W79: =W71-W76 -> 0 | X79: =X71-X76-SUM(X73:X74) -> 0
B80: =$B$67& " Gross MoM" -> 0 Gross MoM | C80: =+SUM(E80:X80)/-D80 -> #DIV/0! | D80: =+D79 -> 0 | E80: =+E79 -> 0 | F80: =+F79 -> 0 | G80: =+G79 -> 0 | H80: =+H79 -> 0 | I80: =+I79 -> 0 | J80: =+J79 -> 0 | K80: =+K79 -> 0 | ... X80: =+X79 -> 0
B82: Upside
D83: 0 | H83: 1 | L83: 2 | P83: 3 | T83: 4 | X83: 5
B84: EBITDA | D84: =+D10 -> 7250 | E84: =+((H84-D84)/4)+D84 -> 7467.5 | F84: =+((H84-D84)/4)+E84 -> 7685 | G84: =+((H84-D84)/4)+F84 -> 7902.5 | H84: =+H10 -> 8120 | I84: =+((L84-H84)/4)+H84 -> 8363.6 | J84: =+((L84-H84)/4)+I84 -> 8607.2 | K84: =+((L84-H84)/4)+J84 -> 8850.8 | L84: =+L10 -> 9094.4 | M84: =+((P84-L84)/4)+L84 -> 9367.232 | N84: =+((P84-L84)/4)+M84 -> 9640.064 | O84: =+((P84-L84)/4)+N84 -> 9912.896 | P84: =+P10 -> 10185.728 | Q84: =+((T84-P84)/4)+P84 -> 10491.3 | R84: =+((T84-P84)/4)+Q84 -> 10796.872 | S84: =+((T84-P84)/4)+R84 -> 11102.444 | T84: =+T10 -> 11408.015 | U84: =+((X84-T84)/4)+T84 -> 11750.256 | V84: =+((X84-T84)/4)+U84 -> 12092.496 | W84: =+((X84-T84)/4)+V84 -> 12434.737 | X84: =+X10 -> 12776.977
B85: EV Multiple | C85: =+Capital_Inputs!F33 -> 6
B86: Enterprise Value | D86: =+$C$85*D84 -> 43500 | E86: =+$C$85*E84 -> 44805 | F86: =+$C$85*F84 -> 46110 | G86: =+$C$85*G84 -> 47415 | H86: =+$C$85*H84 -> 48720 | I86: =+$C$85*I84 -> 50181.6 | J86: =+$C$85*J84 -> 51643.2 | K86: =+$C$85*K84 -> 53104.8 | ... X86: =+$C$85*X84 -> 76661.863
B87: Total Debt | D87: =IF(E87<0,-D29,+D28) -> -28000 | E87: =IF(F87<0,-E29,+E28) -> -28000 | F87: =IF(G87<0,-F29,+F28) -> -28000 | G87: =IF(H87<0,-G29,+G28) -> -28000 | H87: =IF(I87<0,-H29,+H28) -> -26583.607 | I87: =IF(J87<0,-I29,+I28) -> -26583.607 | J87: =IF(K87<0,-J29,+J28) -> -26583.607 | K87: =IF(L87<0,-K29,+K28) -> -26583.607 | ... X87: =IF(Y87<0,-X29,+X28) -> -22334.426
B88: Equity Value | D88: =IF(D87=0,0,+(D84*$C$85)+D87) -> 15500 | E88: =IF(E87=0,0,+(E84*$C$85)+E87) -> 16805 | F88: =IF(F87=0,0,+(F84*$C$85)+F87) -> 18110 | G88: =IF(G87=0,0,+(G84*$C$85)+G87) -> 19415 | H88: =IF(H87=0,0,+(H84*$C$85)+H87) -> 22136.393 | I88: =IF(I87=0,0,+(I84*$C$85)+I87) -> 23597.993 | J88: =IF(J87=0,0,+(J84*$C$85)+J87) -> 25059.593 | K88: =IF(K87=0,0,+(K84*$C$85)+K87) -> 26521.193 | ... X88: =IF(X87=0,0,+(X84*$C$85)+X87) -> 54327.437
B89: =+SUM(Capital_Inputs!F51,Capital_Inputs!F66,Capital_Inputs!F76) -> 0.1 | D89: =+$B$89*D$88 -> 1550 | E89: =+$B$89*E$88 -> 1680.5 | F89: =+$B$89*F$88 -> 1811 | G89: =+$B$89*G$88 -> 1941.5 | H89: =+$B$89*H$88 -> 2213.6393 | I89: =+$B$89*I$88 -> 2359.7993 | J89: =+$B$89*J$88 -> 2505.9593 | K89: =+$B$89*K$88 -> 2652.1193 | ... X89: =+$B$89*X$88 -> 5432.7437
B90: =+Capital_Inputs!F106 -> 0 | D90: =+$B$90*D$88 -> 0 | E90: =+$B$90*E$88 -> 0 | F90: =+$B$90*F$88 -> 0 | G90: =+$B$90*G$88 -> 0 | H90: =+$B$90*H$88 -> 0 | I90: =+$B$90*I$88 -> 0 | J90: =+$B$90*J$88 -> 0 | K90: =+$B$90*K$88 -> 0 | ... X90: =+$B$90*X$88 -> 0
B91: Exit Fee | C91: =SUM(D91:X91) -> 0 | X91: =+Capital_Inputs!F83 -> 0
B92: Total | D92: =+SUM(D89:D91) -> 1550 | E92: =+SUM(E89:E91) -> 1680.5 | F92: =+SUM(F89:F91) -> 1811 | G92: =+SUM(G89:G91) -> 1941.5 | H92: =+SUM(H89:H91) -> 2213.6393 | I92: =+SUM(I89:I91) -> 2359.7993 | J92: =+SUM(J89:J91) -> 2505.9593 | K92: =+SUM(K89:K91) -> 2652.1193 | ... X92: =+SUM(X89:X91) -> 5432.7437
B94: Alternatively: FinCo
B96: =+Capital_Inputs!D85& ": 1st Out tranche" -> RMB: 1st Out tranche
B97: Opening Balance | D97: 0 | E97: =D105 -> 19000 | F97: =E105 -> 19000 | G97: =F105 -> 19000 | H97: =G105 -> 19000 | I97: =H105 -> 17583.607 | J97: =I105 -> 17583.607 | K97: =J105 -> 17583.607 | L97: =K105 -> 17583.607 | ... X97: =W105 -> 13334.426
B98: Advances | D98: =+D23*Capital_Inputs!$F$87 -> 19000 | E98: =+E23*Capital_Inputs!$F$87 -> 0 | F98: =+F23*Capital_Inputs!$F$87 -> 0 | G98: =+G23*Capital_Inputs!$F$87 -> 0 | H98: =+H23*Capital_Inputs!$F$87 -> 0 | I98: =+I23*Capital_Inputs!$F$87 -> 0 | J98: =+J23*Capital_Inputs!$F$87 -> 0 | K98: =+K23*Capital_Inputs!$F$87 -> 0 | ... X98: =+X23*Capital_Inputs!$F$87 -> 0
B99: Arranging Fee | C99: =+Capital_Inputs!F89 -> 0.02 | D99: =+$C$99*D98 -> 380 | E99: =+$C$99*E98 -> 0 | F99: =+$C$99*F98 -> 0 | G99: =+$C$99*G98 -> 0 | H99: =+$C$99*H98 -> 0 | I99: =+$C$99*I98 -> 0 | J99: =+$C$99*J98 -> 0 | K99: =+$C$99*K98 -> 0 | ... X99: =+$C$99*X98 -> 0
B100: Interest | C100: =(AVERAGE(E100:X100)/AVERAGE(E97:X97)*4) -> 0.0825 | E100: =+SUM(E101:E102) -> 391.875 | F100: =+SUM(F101:F102) -> 391.875 | G100: =+SUM(G101:G102) -> 391.875 | H100: =+SUM(H101:H102) -> 391.875 | I100: =+SUM(I101:I102) -> 362.66189 | J100: =+SUM(J101:J102) -> 362.66189 | K100: =+SUM(K101:K102) -> 362.66189 | L100: =+SUM(L101:L102) -> 362.66189 | ... X100: =+SUM(X101:X102) -> 275.02254
B101: Cash Pay | C101: =+Capital_Inputs!F90 -> 0.045 | E101: =IF($C$101=0,0,+($C101+$E$8)*0.25*E$97) -> 391.875 | F101: =IF($C$101=0,0,+($C101+$E$8)*0.25*F$97) -> 391.875 | G101: =IF($C$101=0,0,+($C101+$E$8)*0.25*G$97) -> 391.875 | H101: =IF($C$101=0,0,+($C101+$E$8)*0.25*H$97) -> 391.875 | I101: =IF($C$101=0,0,+($C101+$E$8)*0.25*I$97) -> 362.66189 | J101: =IF($C$101=0,0,+($C101+$E$8)*0.25*J$97) -> 362.66189 | K101: =IF($C$101=0,0,+($C101+$E$8)*0.25*K$97) -> 362.66189 | L101: =IF($C$101=0,0,+($C101+$E$8)*0.25*L$97) -> 362.66189 | ... X101: =IF($C$101=0,0,+($C101+$E$8)*0.25*X$97) -> 275.02254
B102: PIK | C102: =+Capital_Inputs!F91 -> 0 | E102: =IF($C102=0,0,+($C102*0.25*E$97)) -> 0 | F102: =IF($C102=0,0,+($C102*0.25*F$97)) -> 0 | G102: =IF($C102=0,0,+($C102*0.25*G$97)) -> 0 | H102: =IF($C102=0,0,+($C102*0.25*H$97)) -> 0 | I102: =IF($C102=0,0,+($C102*0.25*I$97)) -> 0 | J102: =IF($C102=0,0,+($C102*0.25*J$97)) -> 0 | K102: =IF($C102=0,0,+($C102*0.25*K$97)) -> 0 | L102: =IF($C102=0,0,+($C102*0.25*L$97)) -> 0 | ... X102: =IF($C102=0,0,+($C102*0.25*X$97)) -> 0
B103: Amortisation | C103: =-AVERAGE(E103:X103)/AVERAGE(E97:X97)*4 -> 0.35043602 | H103: =+SUM(H73:H74,H58:H59,H43:H44) -> -1416.3934 | L103: =+SUM(L73:L74,L58:L59,L43:L44) -> -1416.3934 | P103: =+SUM(P73:P74,P58:P59,P43:P44) -> -1416.3934 | T103: =+SUM(T73:T74,T58:T59,T43:T44) -> -1416.3934 | X103: =+SUM(X73:X74,X58:X59,X43:X44) -> -1416.3934
B104: Repayments | E104: =IF(Debt_Model!E$12=Capital_Inputs!$F$18,-E97-E102,IF(E103<0,E103,0)) -> 0 | F104: =IF(Debt_Model!F$12=Capital_Inputs!$F$18,-F97-F102,IF(F103<0,F103,0)) -> 0 | G104: =IF(Debt_Model!G$12=Capital_Inputs!$F$18,-G97-G102,IF(G103<0,G103,0)) -> 0 | H104: =IF(Debt_Model!H$12=Capital_Inputs!$F$18,-H97-H102,IF(H103<0,H103,0)) -> -1416.3934 | I104: =IF(Debt_Model!I$12=Capital_Inputs!$F$18,-I97-I102,IF(I103<0,I103,0)) -> 0 | J104: =IF(Debt_Model!J$12=Capital_Inputs!$F$18,-J97-J102,IF(J103<0,J103,0)) -> 0 | K104: =IF(Debt_Model!K$12=Capital_Inputs!$F$18,-K97-K102,IF(K103<0,K103,0)) -> 0 | L104: =IF(Debt_Model!L$12=Capital_Inputs!$F$18,-L97-L102,IF(L103<0,L103,0)) -> -1416.3934 | ... X104: =IF(Debt_Model!X$12=Capital_Inputs!$F$18,-X97-X102,IF(X103<0,X103,0)) -> -13334.426
B105: Closing Balance | D105: =D97+D98-D104 -> 19000 | E105: =E97+E98+E102+E104 -> 19000 | F105: =F97+F98+F102+F104 -> 19000 | G105: =G97+G98+G102+G104 -> 19000 | H105: =H97+H98+H102+H104 -> 17583.607 | I105: =I97+I98+I102+I104 -> 17583.607 | J105: =J97+J98+J102+J104 -> 17583.607 | K105: =K97+K98+K102+K104 -> 17583.607 | L105: =L97+L98+L102+L104 -> 16167.213 | ... X105: =X97+X98+X102+X104 -> 0
B107: =+Capital_Inputs!D85 & " Contractual IRR" -> RMB Contractual IRR | C107: {=XIRR( _xlfn._xlws.FILTER(D107:X107,$D$11:$X$11<=Capital_Inputs!$F$19), _xlfn._xlws.FILTER(Debt_Model!$D$11:$X$11,Debt_Model!$D$11:$X$11<=Capital_Inputs!$F$19) )} -> 0.0890389 | D107: =-D98+D99 -> -18620 | E107: =+E101-E104+E99-E98 -> 391.875 | F107: =+F101-F104+F99-F98 -> 391.875 | G107: =+G101-G104+G99-G98 -> 391.875 | H107: =+H101-H104+H99-H98 -> 1808.2684 | I107: =+I101-I104+I99-I98 -> 362.66189 | J107: =+J101-J104+J99-J98 -> 362.66189 | K107: =+K101-K104+K99-K98 -> 362.66189 | L107: =+L101-L104+L99-L98 -> 1779.0553 | ... X107: =+X101-X104+X99-X98 -> 13609.449
B108: =+Capital_Inputs!D85 & " Contractual MoM" -> RMB Contractual MoM | C108: =+SUM(E108:X108)/-D108 -> 1.3785701 | D108: =+D107 -> -18620 | E108: =+E107 -> 391.875 | F108: =+F107 -> 391.875 | G108: =+G107 -> 391.875 | H108: =+H107 -> 1808.2684 | I108: =+I107 -> 362.66189 | J108: =+J107 -> 362.66189 | K108: =+K107 -> 362.66189 | ... X108: =+X107 -> 13609.449
B110: Westbrooke: 2nd Out Tranche
B111: Opening Balance | D111: 0 | E111: =D119 -> 9000 | F111: =E119 -> 9000 | G111: =F119 -> 9000 | H111: =G119 -> 9000 | I111: =H119 -> 9000 | J111: =I119 -> 9000 | K111: =J119 -> 9000 | L111: =K119 -> 9000 | ... X111: =W119 -> 9000
B112: Advances | D112: =+D39+D54+D69-D98 -> 9000 | E112: =+E23-E98 -> 0 | F112: =+F23-F98 -> 0 | G112: =+G23-G98 -> 0 | H112: =+H23-H98 -> 0 | I112: =+I23-I98 -> 0 | J112: =+J23-J98 -> 0 | K112: =+K23-K98 -> 0 | L112: =+L23-L98 -> 0 | ... X112: =+X23-X98 -> 0
B113: Arranging Fee | C113: =+D113/D112 -> 0.051111111 | D113: =+SUM(D40,D55,D70)-D99 -> 460 | E113: =+SUM(E40,E55,E70)-E99 -> 0 | F113: =+SUM(F40,F55,F70)-F99 -> 0 | G113: =+SUM(G40,G55,G70)-G99 -> 0 | H113: =+SUM(H40,H55,H70)-H99 -> 0 | I113: =+SUM(I40,I55,I70)-I99 -> 0 | J113: =+SUM(J40,J55,J70)-J99 -> 0 | K113: =+SUM(K40,K55,K70)-K99 -> 0 | ... X113: =+SUM(X40,X55,X70)-X99 -> 0
B114: Interest | C114: =(AVERAGE(E114:X114)/AVERAGE(E111:X111)*4) -> 0.23287158 | E114: =+SUM(E115:E116) -> 538.125 | F114: =+SUM(F115:F116) -> 538.125 | G114: =+SUM(G115:G116) -> 538.125 | H114: =+SUM(H115:H116) -> 538.125 | I114: =+SUM(I115:I116) -> 531.04303 | J114: =+SUM(J115:J116) -> 531.04303 | K114: =+SUM(K115:K116) -> 531.04303 | L114: =+SUM(L115:L116) -> 531.04303 | ... X114: =+SUM(X115:X116) -> 509.79713
B115: Cash Pay | C115: =(AVERAGE(E115:X115)/AVERAGE(E111:X111)*4) -> 0.23287158 | E115: =+E41+E56+E71-E101 -> 538.125 | F115: =+F41+F56+F71-F101 -> 538.125 | G115: =+G41+G56+G71-G101 -> 538.125 | H115: =+H41+H56+H71-H101 -> 538.125 | I115: =+I41+I56+I71-I101 -> 531.04303 | J115: =+J41+J56+J71-J101 -> 531.04303 | K115: =+K41+K56+K71-K101 -> 531.04303 | L115: =+L41+L56+L71-L101 -> 531.04303 | ... X115: =+X41+X56+X71-X101 -> 509.79713 | AI115: 40.535 | AJ115: 44.062
B116: PIK | C116: =AVERAGE(E116:X116)/AVERAGE(E111:X111)*4 -> 0 | E116: =+E42+E57+E72-E102 -> 0 | F116: =+F42+F57+F72-F102 -> 0 | G116: =+G42+G57+G72-G102 -> 0 | H116: =+H42+H57+H72-H102 -> 0 | I116: =+I42+I57+I72-I102 -> 0 | J116: =+J42+J57+J72-J102 -> 0 | K116: =+K42+K57+K72-K102 -> 0 | L116: =+L42+L57+L72-L102 -> 0 | ... X116: =+X42+X57+X72-X102 -> 0 | AI116: 2.587 | AJ116: 3.005
B117: Amortisation | C117: =-AVERAGE(E117:X117)/AVERAGE(E111:X111)*4 -> 0 | H117: 0 | L117: 0 | P117: 0 | T117: 0 | X117: 0
B118: Repayments | E118: =IF(Debt_Model!E$12=Capital_Inputs!$F$18,-E111-E116,IF(E117<0,E117,0)) -> 0 | F118: =IF(Debt_Model!F$12=Capital_Inputs!$F$18,-F111-F116,IF(F117<0,F117,0)) -> 0 | G118: =IF(Debt_Model!G$12=Capital_Inputs!$F$18,-G111-G116,IF(G117<0,G117,0)) -> 0 | H118: =IF(Debt_Model!H$12=Capital_Inputs!$F$18,-H111-H116,IF(H117<0,H117,0)) -> 0 | I118: =IF(Debt_Model!I$12=Capital_Inputs!$F$18,-I111-I116,IF(I117<0,I117,0)) -> 0 | J118: =IF(Debt_Model!J$12=Capital_Inputs!$F$18,-J111-J116,IF(J117<0,J117,0)) -> 0 | K118: =IF(Debt_Model!K$12=Capital_Inputs!$F$18,-K111-K116,IF(K117<0,K117,0)) -> 0 | L118: =IF(Debt_Model!L$12=Capital_Inputs!$F$18,-L111-L116,IF(L117<0,L117,0)) -> 0 | ... X118: =IF(Debt_Model!X$12=Capital_Inputs!$F$18,-X111-X116,IF(X117<0,X117,0)) -> -9000 | AI118: =AI116/AI115 -> 0.063821389 | AJ118: =AJ116/AJ115 -> 0.068199355
B119: Closing Balance | D119: =D111+D112-D118 -> 9000 | E119: =E111+E112+E116+E118 -> 9000 | F119: =F111+F112+F116+F118 -> 9000 | G119: =G111+G112+G116+G118 -> 9000 | H119: =H111+H112+H116+H118 -> 9000 | I119: =I111+I112+I116+I118 -> 9000 | J119: =J111+J112+J116+J118 -> 9000 | K119: =K111+K112+K116+K118 -> 9000 | L119: =L111+L112+L116+L118 -> 9000 | ... X119: =X111+X112+X116+X118 -> 0
...

Sheet Capital_Inputs
A1: x | I1: x
B2: =+D7 -> Project X
B3: {=MID(CELL("filename",A1),FIND("]",CELL("filename",A1))+1,255)} -> Capital_Inputs
B4: =F11& ", unless stated otherwise" -> £000's, unless stated otherwise
D7: Project X
C9: Static Assumptions
D11: Units | E11: £ | F11: £000's
D13: Entry Assumptions:
D14: Entry date: | E14: DMY | F14: =+TODAY() -> 46143
D16: Exit Assumptions:
D17: Investment term | E17: m | F17: 60
D18: Investment exit quarter | E18: m | F18: =MROUND(F17,3) -> 60
D19: Exit date: | E19: DMY | F19: =+EOMONTH(F14,F18) -> 47999
D20: Investment term | E20: y | F20: =YEARFRAC(F14,F19) -> 5.0833333
D22: Structure:
D23: Tranche 1: | F23: Unitranche
D24: Tranche 2: | F24: Preferred Equity
D25: Tranche 3:
D27: Structuring:
D28: Structuring EBITDA | E28: £000's | F28: 7250
D29: Structuring CFADS | E29: £000's | F29: 6981
D31: EV Multiples:
D32: Entry Multiple | E32: x | F32: 6
D33: Exit Multiple | E33: x | F33: 6
C35: Case assumptions
D37: P&L assumptions:
D38: EBITDA CAGR | E38: % | F38: 0.12
D39: CFADS | E39: % | F39: 0.7
C41: Debt Funding
D43: =+F23 & ":" -> Unitranche:
D44: Quantum | E44: £'m | F44: 18
D45: Implied Gross Leverage | E45: x | F45: =+F44/(Debt_Model!$D$10/1000) -> 2.4827586
D46: Arrangement Fee | E46: % | F46: 0.03
D47: Cash Margin | E47: % | F47: 0.065
D48: PIK Margin | E48: % | F48: 0
D49: Amortisation | E49: % | F49: 0.4
D50: Amortisation | E50: £'m | F50: =+F49*F44 -> 7.2
D51: Warrant | E51: % | F51: 0.1
D53: =+F24& ":" -> Preferred Equity:
D54: Max quantum | E54: £'m | F54: 10
D55: Quantum drawn | E55: £'m | F55: 10
D56: Implied Gross Leverage | E56: x | F56: =+F55/(Debt_Model!$D$10/1000)+F45 -> 3.862069
D57: Arrangement Fee | E57: % | F57: 0.03
D58: Arrangement Fee payment 1 | E58: DMY | F58: =+F14 -> 46143
D59: Amount due | E59: % | F59: 1
D60: Arrangement Fee payment 2 | E60: DMY | F60: =EOMONTH(F58,12) -> 46538
D61: Amount due | E61: % | F61: 0
D62: Cash Margin | E62: % | F62: 0.15
D63: PIK Margin | E63: % | F63: 0
D64: Amortisation | E64: % | F64: 0
D65: Amortisation | E65: £'m | F65: =+F64*F55 -> 0
D66: Warrant | E66: % | F66: 0
D68: =+F25& ":" -> :
D69: Quantum | E69: £'m | F69: 0
D70: Implied Gross Leverage | E70: x | F70: =+F69/(Debt_Model!$D$10/1000)+F56 -> 3.862069
D71: Arrangement Fee | E71: % | F71: 0
D72: Cash Margin | E72: % | F72: 0
D73: PIK Margin | E73: % | F73: 0
D74: Amortisation | E74: % | F74: 0
D75: Amortisation | E75: £'m | F75: =+F74*F69 -> 0
D76: Warrant | E76: % | F76: 0
D78: Upside
D79: Quantum | E79: £'m | F79: 0
D80: Arrangement Fee | E80: % | F80: 0
D81: PIK Margin | E81: % | F81: 0
D82: Shareholding | E82: % | F82: 0
D83: Exit Fee | E83: £000's | F83: 0
D85: RMB | F85: TRUE
D86: Quantum | E86: £'m | F86: 19
D87: Proportion of total funds | E87: % | F87: =1-F98 -> 0.67857143
D88: Implied Gross Leverage | E88: x | F88: =+F86/(Debt_Model!$D$10/1000) -> 2.6206897
D89: Arrangement Fee | E89: % | F89: 0.02
D90: Cash Margin | E90: % | F90: 0.045
D91: PIK Margin | E91: % | F91: 0
D92: Amortisation | E92: % | F92: =+F50/F86 -> 0.37894737
D93: Amortisation | E93: £'m | F93: =+F92*F86 -> 7.2
D94: Warrant | E94: % | F94: 0
D96: WDO (Day 1)
D97: Quantum | E97: £'m | F97: =+F44+F55+F69+F79-F86 -> 9
D98: Proportion of total funds | E98: % | F98: =+F97/(F44+F55+F69) -> 0.32142857
D99: Implied Gross Leverage | E99: x | F99: =+F97/(Debt_Model!$D$10/1000)+F88 -> 3.862069
D100: Arrangement Fee | E100: % | F100: =Debt_Model!C113 -> 0.051111111
D101: Cash Margin | E101: % | F101: =+Debt_Model!C115 -> 0.23287158
D102: PIK Margin | E102: % | F102: =+Debt_Model!C116 -> 0
D103: Amortisation | E103: % | F103: =+Debt_Model!C117 -> 0
D104: Amortisation | E104: £'m | F104: =+F103*F97 -> 0
D105: Warrant | E105: % | F105: =+F51+F66+F76-F94 -> 0.1
D106: Equity Shareholding | F106: =+F82 -> 0
C108: WAAM Fees
D110: Deal-level WAAM Fees
D111: Monitoring Fees | E111: £000's | F111: 25
D112: Arrangement Fee | E112: % | F112: 0.02
D113: Arrangement Fee Skim | E113: % | F113: 0.5
D114: Performance Fee | E114: % | F114: 0.15
D116: Above hurdle of | E116: % | F116: 0.08
D117: Advisory Fee | E117: % | F117: 0.015
A119: x | I119: x
D121: Working
D123: Senior | F123: Stretch Senior
D124: Unitranche | F124: Hybrid
...

Sheet Output
A1: x | J1: x
B2: =Capital_Inputs!D7 -> Project X
B3: {=MID(CELL("filename",A1),FIND("]",CELL("filename",A1))+1,255)} -> Output
B4: =+Capital_Inputs!F11 & ", unless stated otherwise" -> £000's, unless stated otherwise
B7: Returns attribution | F7: IRR | H7: MoM
B9: WDO Gross | F9: % | G9: =+Debt_Model!C130 -> 0.33679906 | H9: x | I9: =+Debt_Model!C131 -> 2.9170919
B10: WDO Net | F10: % | G10: =+Debt_Model!C133 -> 0.31972077 | H10: x | I10: =+Debt_Model!C134 -> 2.8535607
B11: Contractual | F11: % | G11: =+Debt_Model!C196 -> 0.26911617 | H11: x | I11: {=+SUM(Debt_Model!E196:X196/-Debt_Model!D196)} -> 2.2809393
B12: Amortisation | F12: % | G12: =+Debt_Model!C203 -> 0
B13: Interest - PIK | F13: % | G13: =+Debt_Model!C201 -> 0
B14: Interest - Cash | F14: % | G14: =+Debt_Model!C197 -> 0.24802756
B15: Arrangement Fee | F15: % | G15: =+Debt_Model!C199 -> 0.021088612
B16: Equity / Warrant | F16: % | G16: =+Debt_Model!C205 -> 0.067682886
B17: RMB | F17: % | G17: =+Debt_Model!C136 -> 0.0890389 | H17: x | I17: =+Debt_Model!C137 -> 1.3785701
B19: Dashboard | D19: =+EOMONTH(Capital_Inputs!F14,-12) -> 45808 | E19: =+Capital_Inputs!F14 -> 46143 | F19: =+EOMONTH(E19,12) -> 46538 | G19: =+EOMONTH(F19,12) -> 46904 | H19: =+EOMONTH(G19,12) -> 47269 | I19: =+EOMONTH(H19,12) -> 47634
B21: EBITDA | D21: =+Debt_Model!D10 -> 7250 | E21: =+Debt_Model!H10 -> 8120 | F21: =+Debt_Model!L10 -> 9094.4 | G21: =+Debt_Model!P10 -> 10185.728 | H21: =+Debt_Model!T10 -> 11408.015 | I21: =+Debt_Model!X10 -> 12776.977
B22: % Growth | E22: =E21/D21-1 -> 0.12 | F22: =F21/E21-1 -> 0.12 | G22: =G21/F21-1 -> 0.12 | H22: =H21/G21-1 -> 0.12 | I22: =I21/H21-1 -> 0.12
B24: CFADS | D24: =+Capital_Inputs!F29 -> 6981 | E24: =+E21*Capital_Inputs!$F$39 -> 5684 | F24: =+F21*Capital_Inputs!$F$39 -> 6366.08 | G24: =+G21*Capital_Inputs!$F$39 -> 7130.0096 | H24: =+H21*Capital_Inputs!$F$39 -> 7985.6108 | I24: =+I21*Capital_Inputs!$F$39 -> 8943.884
B25: % GM | D25: =+D24/D$21 -> 0.96289655 | E25: =+E24/E$21 -> 0.7 | F25: =+F24/F$21 -> 0.7 | G25: =+G24/G$21 -> 0.7 | H25: =+H24/H$21 -> 0.7 | I25: =+I24/I$21 -> 0.7
B27: Debt Service | E27: =-SUM(Debt_Model!E25:H25)+Debt_Model!H27 -> -5136.3934 | F27: =-SUM(Debt_Model!I25:L25)+Debt_Model!L27 -> -4991.2131 | G27: =-SUM(Debt_Model!M25:P25)+Debt_Model!P27 -> -4846.0328 | H27: =-SUM(Debt_Model!Q25:T25)+Debt_Model!T27 -> -4700.8525 | I27: =-SUM(Debt_Model!U25:X25)+Debt_Model!X27 -> -4555.6721
B29: Net Cash | E29: =+E27+E24 -> 547.60656 | F29: =+F27+F24 -> 1374.8669 | G29: =+G27+G24 -> 2283.9768 | H29: =+H27+H24 -> 3284.7583 | I29: =+I27+I24 -> 4388.2119
B31: KPIs
B33: Senior Facility xEBITDA | D33: =+Debt_Model!$D$47/Output!D21 -> 2.4827586 | E33: =+Debt_Model!$H$47/Output!E21 -> 2.0423161 | F33: =+Debt_Model!$L$47/Output!F21 -> 1.667753 | G33: =+Debt_Model!$P$47/Output!G21 -> 1.3500085 | H33: =+Debt_Model!$T$47/Output!H21 -> 1.081207 | I33: =-Debt_Model!$X$46/Output!I21 -> 0.96536341
B34: Global Facility xEBITDA | D34: =+Debt_Model!$D$29/D21 -> 3.862069 | E34: =+Debt_Model!$H$29/E21 -> 3.2738432 | F34: =+Debt_Model!$L$29/F21 -> 2.7673308 | G34: =+Debt_Model!$P$29/G21 -> 2.3317744 | H34: =+Debt_Model!$T$29/H21 -> 1.9577837 | I34: =+Debt_Model!$X$28/-I21 -> 1.7480211
B35: Senior Facility xCFADS | D35: =+Debt_Model!$D$47/D24 -> 2.5784272 | E35: =+Debt_Model!$H$47/E24 -> 2.9175944 | F35: =+Debt_Model!$H$47/F24 -> 2.604995 | G35: =+Debt_Model!$H$47/G24 -> 2.3258884 | H35: =+Debt_Model!$H$47/H24 -> 2.0766861 | I35: =+Debt_Model!$H$47/I24 -> 1.854184
B36: Global Facility xCFADS | D36: =+Debt_Model!$D$29/D24 -> 4.0108867 | E36: =+Debt_Model!$H$29/E24 -> 4.6769188 | F36: =+Debt_Model!$H$29/F24 -> 4.1758204 | G36: =+Debt_Model!$H$29/G24 -> 3.728411 | H36: =+Debt_Model!$H$29/H24 -> 3.3289384 | I36: =+Debt_Model!$H$29/I24 -> 2.9722665
B37: DSCR | E37: =-E24/E27 -> 1.106613 | F37: =-F24/F27 -> 1.2754575 | G37: =-G24/G27 -> 1.4713086 | H37: =-H24/H27 -> 1.698758 | I37: =-I24/I27 -> 1.9632414
A39: x | J39: x
